ansys/stk/__init__.py
ansys/stk/core/__init__.py
ansys/stk/core/analysis_workbench.py
ansys/stk/core/graphics.py
ansys/stk/core/stkdesktop.py
ansys/stk/core/stkruntime.py
ansys/stk/core/stkutil.py
ansys/stk/core/stkx.py
ansys/stk/core/uiapplication.py
ansys/stk/core/uicore.py
ansys/stk/core/internal/AgGrpcServices_pb2.py
ansys/stk/core/internal/AgGrpcServices_pb2_grpc.py
ansys/stk/core/internal/__init__.py
ansys/stk/core/internal/apiutil.py
ansys/stk/core/internal/coclassutil.py
ansys/stk/core/internal/comevents.py
ansys/stk/core/internal/comutil.py
ansys/stk/core/internal/cyberchannel.py
ansys/stk/core/internal/dataanalysisutil.py
ansys/stk/core/internal/eventutil.py
ansys/stk/core/internal/grpcevents.py
ansys/stk/core/internal/grpcutil.py
ansys/stk/core/internal/marshall.py
ansys/stk/core/internal/stkxinitialization.py
ansys/stk/core/internal/stkxrfb.py
ansys/stk/core/internal/timerutil.py
ansys/stk/core/stkengine/__init__.py
ansys/stk/core/stkengine/tkcontrols.py
ansys/stk/core/stkengine/experimental/__init__.py
ansys/stk/core/stkengine/experimental/jupyterwidgets.py
ansys/stk/core/stkobjects/__init__.py
ansys/stk/core/stkobjects/astrogator.py
ansys/stk/core/stkobjects/aviator/__init__.py
ansys/stk/core/stkobjects/aviator/matlab.py
ansys/stk/core/stkrfchannelmodeler/__init__.py
ansys/stk/core/tools/api_migration_assistant/__init__.py
ansys/stk/core/tools/api_migration_assistant/__main__.py
ansys/stk/core/tools/api_migration_assistant/api_migration_assistant.py
ansys/stk/core/tools/api_migration_assistant/argument_parser.py
ansys/stk/core/tools/api_migration_assistant/call_record.py
ansys/stk/core/tools/api_migration_assistant/code_editor.py
ansys/stk/core/tools/api_migration_assistant/mappings.py
ansys/stk/core/tools/api_migration_assistant/migration_transformer.py
ansys/stk/core/tools/api_migration_assistant/recorder.py
ansys/stk/core/tools/api_migration_assistant/recording.py
ansys/stk/core/tools/api_migration_assistant/api-mappings/agi.stk13.graphics.json
ansys_stk-0.2.1.dist-info/entry_points.txt
ansys_stk-0.2.1.dist-info/licenses/LICENSE
ansys_stk-0.2.1.dist-info/WHEEL
ansys_stk-0.2.1.dist-info/METADATA
ansys_stk-0.2.1.dist-info/RECORD
