Metadata-Version: 2.4
Name: ansys-stk
Version: 0.2.1
Summary: The next generation Python API for STK.
Author-email: "ANSYS, Inc." <pyansys.core@ansys.com>
Maintainer-email: "ANSYS, Inc." <pyansys.core@ansys.com>
Requires-Python: >=3.10
License-Expression: MIT
Classifier: Development Status :: 4 - Beta
Classifier: Intended Audience :: Developers
Classifier: Intended Audience :: Science/Research
Classifier: Operating System :: OS Independent
Classifier: Programming Language :: Python :: 3 :: Only
Classifier: Programming Language :: Python :: 3.10
Classifier: Programming Language :: Python :: 3.11
Classifier: Programming Language :: Python :: 3.12
Classifier: Programming Language :: Python :: 3.13
Classifier: Programming Language :: Python :: 3.14
Classifier: Topic :: Scientific/Engineering :: Information Analysis
Classifier: Topic :: Scientific/Engineering :: Physics
Classifier: Topic :: Software Development :: Libraries
License-File: LICENSE
Requires-Dist: grpcio>=1.73.1 ; extra == "all"
Requires-Dist: jupyter-rfb>=0.5.3 ; extra == "all"
Requires-Dist: libcst>=1.8.2 ; extra == "all"
Requires-Dist: matplotlib>=3.10.3 ; extra == "all"
Requires-Dist: numpy>=2.2.6 ; extra == "all"
Requires-Dist: pandas>=2.3.1 ; extra == "all"
Requires-Dist: pillow>=11.3.0 ; extra == "all"
Requires-Dist: protobuf>=6.31.1 ; extra == "all"
Requires-Dist: sidecar>=0.7.0 ; extra == "all"
Requires-Dist: simplejpeg>=1.8.2 ; extra == "all"
Requires-Dist: matplotlib>=3.10.3 ; extra == "extensions"
Requires-Dist: pandas>=2.3.1 ; extra == "extensions"
Requires-Dist: grpcio>=1.73.1 ; extra == "grpc"
Requires-Dist: protobuf>=6.31.1 ; extra == "grpc"
Requires-Dist: jupyter-rfb>=0.5.3 ; extra == "jupyter"
Requires-Dist: numpy>=2.2.6 ; extra == "jupyter"
Requires-Dist: pillow>=11.3.0 ; extra == "jupyter"
Requires-Dist: sidecar>=0.7.0 ; extra == "jupyter"
Requires-Dist: simplejpeg>=1.8.2 ; extra == "jupyter"
Requires-Dist: libcst>=1.8.2 ; extra == "migration"
Project-URL: Changelog, https://github.com/ansys/pystk/blob/main/doc/source/changelog.rst
Project-URL: Discussions, https://github.com/ansys/pystk/discussions
Project-URL: Documentation, https://stk.docs.pyansys.com/
Project-URL: Homepage, https://www.ansys.com/products/missions/ansys-stk
Project-URL: Issues, https://github.com/ansys/pystk/issues
Project-URL: Source, https://github.com/ansys/pystk
Provides-Extra: all
Provides-Extra: core
Provides-Extra: extensions
Provides-Extra: grpc
Provides-Extra: jupyter
Provides-Extra: migration
